{"swagger":"2.0","info":{"description":"Api Documentation","version":"1.0","title":"Api Documentation","termsOfService":"urn:tos","contact":{},"license":{"name":"Apache 2.0","url":"http://www.apache.org/licenses/LICENSE-2.0"}},"host":"localhost:8090","basePath":"/falcoservice","tags":[{"name":"room-controller","description":"Room Controller"},{"name":"booking-controller","description":"Booking Controller"},{"name":"room-type-controller","description":"Room Type Controller"}],"paths":{"/api/v1/booking/adddaytobooking/{bookingid}/{roomid}/{reservationdate}/{nights}":{"post":{"tags":["booking-controller"],"summary":"addDay","operationId":"addDayUsingPOST","consumes":["application/json"],"produces":["*/*"],"parameters":[{"name":"bookingid","in":"path","description":"bookingid","required":true,"type":"integer","format":"int64"},{"name":"roomid","in":"path","description":"roomid","required":true,"type":"integer","format":"int32"},{"name":"reservationdate","in":"path","description":"reservationdate","required":true,"type":"string"},{"name":"nights","in":"path","description":"nights","required":true,"type":"integer","format":"int32"}],"responses":{"200":{"description":"OK"},"201":{"description":"Created"},"401":{"description":"Unauthorized"},"403":{"description":"Forbidden"},"404":{"description":"Not Found"}}}},"/api/v1/booking/delete":{"delete":{"tags":["booking-controller"],"summary":"delete","operationId":"deleteUsingDELETE","consumes":["application/json"],"produces":["*/*"],"parameters":[{"name":"bookingId","in":"query","required":false,"type":"integer","format":"int64"},{"name":"customerName","in":"query","required":false,"type":"string"},{"name":"code","in":"query","required":false,"type":"string"},{"name":"roomId","in":"query","required":false,"type":"integer","format":"int32"},{"name":"nightNumbers","in":"query","required":false,"type":"integer","format":"int32"},{"name":"bookingDate","in":"query","required":false,"type":"string"},{"name":"sourceBooking","in":"query","required":false,"type":"string","enum":["BOOKING","EXTERNAL"]},{"name":"details","in":"query","required":false,"type":"string"},{"name":"paid","in":"query","required":false,"type":"string","enum":["PAGATO","NON_PAGATO"]},{"name":"deposit","in":"query","required":false,"type":"string"},{"name":"guests","in":"query","required":false,"type":"integer","format":"int32"},{"name":"total","in":"query","required":false,"type":"string"}],"responses":{"200":{"description":"OK"},"401":{"description":"Unauthorized"},"204":{"description":"No Content"},"403":{"description":"Forbidden"}}}},"/api/v1/booking/deletebycode/{code}":{"get":{"tags":["booking-controller"],"summary":"deleteBookTypeById","operationId":"deleteBookTypeByIdUsingGET","consumes":["application/json"],"produces":["*/*"],"parameters":[{"name":"code","in":"path","description":"code","required":true,"type":"string"}],"responses":{"200":{"description":"OK"},"401":{"description":"Unauthorized"},"403":{"description":"Forbidden"},"404":{"description":"Not Found"}}}},"/api/v1/booking/deletebyid/{id}":{"get":{"tags":["booking-controller"],"summary":"deleteBookTypeById","operationId":"deleteBookTypeByIdUsingGET_1","consumes":["application/json"],"produces":["*/*"],"parameters":[{"name":"id","in":"path","description":"id","required":true,"type":"integer","format":"int64"}],"responses":{"200":{"description":"OK"},"401":{"description":"Unauthorized"},"403":{"description":"Forbidden"},"404":{"description":"Not Found"}}}},"/api/v1/booking/findByCode/{code}":{"get":{"tags":["booking-controller"],"summary":"findByCode","operationId":"findByCodeUsingGET","consumes":["application/json"],"produces":["*/*"],"parameters":[{"name":"code","in":"path","description":"code","required":true,"type":"string"}],"responses":{"200":{"description":"OK","schema":{"type":"array","items":{"$ref":"#/definitions/BookingModel"}}},"401":{"description":"Unauthorized"},"403":{"description":"Forbidden"},"404":{"description":"Not Found"}}}},"/api/v1/booking/findall":{"get":{"tags":["booking-controller"],"summary":"retrieveAll","operationId":"retrieveAllUsingGET","consumes":["application/json"],"produces":["*/*"],"responses":{"200":{"description":"OK","schema":{"type":"array","items":{"$ref":"#/definitions/BookingModel"}}},"401":{"description":"Unauthorized"},"403":{"description":"Forbidden"},"404":{"description":"Not Found"}}}},"/api/v1/booking/movereservation":{"post":{"tags":["booking-controller"],"summary":"moveReservation","operationId":"moveReservationUsingPOST","consumes":["application/json"],"produces":["*/*"],"parameters":[{"name":"bookingId","in":"query","required":false,"type":"integer","format":"int64"},{"name":"customerName","in":"query","required":false,"type":"string"},{"name":"code","in":"query","required":false,"type":"string"},{"name":"roomId","in":"query","required":false,"type":"integer","format":"int32"},{"name":"nightNumbers","in":"query","required":false,"type":"integer","format":"int32"},{"name":"bookingDate","in":"query","required":false,"type":"string"},{"name":"sourceBooking","in":"query","required":false,"type":"string","enum":["BOOKING","EXTERNAL"]},{"name":"details","in":"query","required":false,"type":"string"},{"name":"paid","in":"query","required":false,"type":"string","enum":["PAGATO","NON_PAGATO"]},{"name":"deposit","in":"query","required":false,"type":"string"},{"name":"guests","in":"query","required":false,"type":"integer","format":"int32"},{"name":"total","in":"query","required":false,"type":"string"}],"responses":{"200":{"description":"OK"},"201":{"description":"Created"},"401":{"description":"Unauthorized"},"403":{"description":"Forbidden"},"404":{"description":"Not Found"}}}},"/api/v1/booking/save":{"post":{"tags":["booking-controller"],"summary":"save","operationId":"saveUsingPOST","consumes":["application/json"],"produces":["*/*"],"parameters":[{"name":"bookingId","in":"query","required":false,"type":"integer","format":"int64"},{"name":"customerName","in":"query","required":false,"type":"string"},{"name":"code","in":"query","required":false,"type":"string"},{"name":"roomId","in":"query","required":false,"type":"integer","format":"int32"},{"name":"nightNumbers","in":"query","required":false,"type":"integer","format":"int32"},{"name":"bookingDate","in":"query","required":false,"type":"string"},{"name":"sourceBooking","in":"query","required":false,"type":"string","enum":["BOOKING","EXTERNAL"]},{"name":"details","in":"query","required":false,"type":"string"},{"name":"paid","in":"query","required":false,"type":"string","enum":["PAGATO","NON_PAGATO"]},{"name":"deposit","in":"query","required":false,"type":"string"},{"name":"guests","in":"query","required":false,"type":"integer","format":"int32"},{"name":"total","in":"query","required":false,"type":"string"}],"responses":{"200":{"description":"OK"},"201":{"description":"Created"},"401":{"description":"Unauthorized"},"403":{"description":"Forbidden"},"404":{"description":"Not Found"}}}},"/api/v1/booking/update":{"put":{"tags":["booking-controller"],"summary":"updateBooking","operationId":"updateBookingUsingPUT","consumes":["application/json"],"produces":["*/*"],"parameters":[{"name":"bookingId","in":"query","required":false,"type":"integer","format":"int64"},{"name":"customerName","in":"query","required":false,"type":"string"},{"name":"code","in":"query","required":false,"type":"string"},{"name":"roomId","in":"query","required":false,"type":"integer","format":"int32"},{"name":"nightNumbers","in":"query","required":false,"type":"integer","format":"int32"},{"name":"bookingDate","in":"query","required":false,"type":"string"},{"name":"sourceBooking","in":"query","required":false,"type":"string","enum":["BOOKING","EXTERNAL"]},{"name":"details","in":"query","required":false,"type":"string"},{"name":"paid","in":"query","required":false,"type":"string","enum":["PAGATO","NON_PAGATO"]},{"name":"deposit","in":"query","required":false,"type":"string"},{"name":"guests","in":"query","required":false,"type":"integer","format":"int32"},{"name":"total","in":"query","required":false,"type":"string"}],"responses":{"200":{"description":"OK"},"201":{"description":"Created"},"401":{"description":"Unauthorized"},"403":{"description":"Forbidden"},"404":{"description":"Not Found"}}}},"/api/v1/room/delete":{"delete":{"tags":["room-controller"],"summary":"deleteRoom","operationId":"deleteRoomUsingDELETE","consumes":["application/json"],"produces":["*/*"],"parameters":[{"name":"roomTypeModel.roomTypeId","in":"query","required":false,"type":"integer","format":"int64"},{"name":"roomTypeModel.typeName","in":"query","required":false,"type":"string"},{"name":"roomTypeModel.guests","in":"query","required":false,"type":"integer","format":"int32"},{"name":"roomTypeModel.bedType","in":"query","required":false,"type":"string","enum":["SINGOLO_X_1","SINGOLO_X_2","SINGOLO_X_3","SINGOLO_X_4","DOPPIO_X_1","DOPPIO_X_2","MATRIMONIALE_X_1","MATRIMONIALE_X_1_SINGOLO_X_1","MATRIMONIALE_X_1_SINGOLO_X_2","MATRIMONIALE_X_2_SINGOLO_X_1","MATRIMONIALE_X_2_SINGOLO_X_2","KING_X_1","KING_X_1_SINGOLO_X_1"]},{"name":"roomId","in":"query","required":false,"type":"integer","format":"int64"},{"name":"roomNumber","in":"query","required":false,"type":"integer","format":"int32"}],"responses":{"200":{"description":"OK"},"401":{"description":"Unauthorized"},"204":{"description":"No Content"},"403":{"description":"Forbidden"}}}},"/api/v1/room/deletebyid/{id}":{"get":{"tags":["room-controller"],"summary":"deleteRoomTypeById","operationId":"deleteRoomTypeByIdUsingGET","consumes":["application/json"],"produces":["*/*"],"parameters":[{"name":"id","in":"path","description":"id","required":true,"type":"integer","format":"int64"}],"responses":{"200":{"description":"OK"},"401":{"description":"Unauthorized"},"403":{"description":"Forbidden"},"404":{"description":"Not Found"}}}},"/api/v1/room/findall":{"get":{"tags":["room-controller"],"summary":"retrieveAll","operationId":"retrieveAllUsingGET_1","consumes":["application/json"],"produces":["*/*"],"responses":{"200":{"description":"OK","schema":{"type":"array","items":{"$ref":"#/definitions/RoomModel"}}},"401":{"description":"Unauthorized"},"403":{"description":"Forbidden"},"404":{"description":"Not Found"}}}},"/api/v1/room/save":{"post":{"tags":["room-controller"],"summary":"insertRoom","operationId":"insertRoomUsingPOST","consumes":["application/json"],"produces":["*/*"],"parameters":[{"name":"roomTypeModel.roomTypeId","in":"query","required":false,"type":"integer","format":"int64"},{"name":"roomTypeModel.typeName","in":"query","required":false,"type":"string"},{"name":"roomTypeModel.guests","in":"query","required":false,"type":"integer","format":"int32"},{"name":"roomTypeModel.bedType","in":"query","required":false,"type":"string","enum":["SINGOLO_X_1","SINGOLO_X_2","SINGOLO_X_3","SINGOLO_X_4","DOPPIO_X_1","DOPPIO_X_2","MATRIMONIALE_X_1","MATRIMONIALE_X_1_SINGOLO_X_1","MATRIMONIALE_X_1_SINGOLO_X_2","MATRIMONIALE_X_2_SINGOLO_X_1","MATRIMONIALE_X_2_SINGOLO_X_2","KING_X_1","KING_X_1_SINGOLO_X_1"]},{"name":"roomId","in":"query","required":false,"type":"integer","format":"int64"},{"name":"roomNumber","in":"query","required":false,"type":"integer","format":"int32"}],"responses":{"200":{"description":"OK"},"201":{"description":"Created"},"401":{"description":"Unauthorized"},"403":{"description":"Forbidden"},"404":{"description":"Not Found"}}}},"/api/v1/room/update":{"put":{"tags":["room-controller"],"summary":"updateRoom","operationId":"updateRoomUsingPUT","consumes":["application/json"],"produces":["*/*"],"parameters":[{"name":"roomTypeModel.roomTypeId","in":"query","required":false,"type":"integer","format":"int64"},{"name":"roomTypeModel.typeName","in":"query","required":false,"type":"string"},{"name":"roomTypeModel.guests","in":"query","required":false,"type":"integer","format":"int32"},{"name":"roomTypeModel.bedType","in":"query","required":false,"type":"string","enum":["SINGOLO_X_1","SINGOLO_X_2","SINGOLO_X_3","SINGOLO_X_4","DOPPIO_X_1","DOPPIO_X_2","MATRIMONIALE_X_1","MATRIMONIALE_X_1_SINGOLO_X_1","MATRIMONIALE_X_1_SINGOLO_X_2","MATRIMONIALE_X_2_SINGOLO_X_1","MATRIMONIALE_X_2_SINGOLO_X_2","KING_X_1","KING_X_1_SINGOLO_X_1"]},{"name":"roomId","in":"query","required":false,"type":"integer","format":"int64"},{"name":"roomNumber","in":"query","required":false,"type":"integer","format":"int32"}],"responses":{"200":{"description":"OK"},"201":{"description":"Created"},"401":{"description":"Unauthorized"},"403":{"description":"Forbidden"},"404":{"description":"Not Found"}}}},"/api/v1/roomtype/delete":{"delete":{"tags":["room-type-controller"],"summary":"deleteRoomType","operationId":"deleteRoomTypeUsingDELETE","consumes":["application/json"],"produces":["*/*"],"parameters":[{"name":"roomTypeId","in":"query","required":false,"type":"integer","format":"int64"},{"name":"typeName","in":"query","required":false,"type":"string"},{"name":"guests","in":"query","required":false,"type":"integer","format":"int32"},{"name":"bedType","in":"query","required":false,"type":"string","enum":["SINGOLO_X_1","SINGOLO_X_2","SINGOLO_X_3","SINGOLO_X_4","DOPPIO_X_1","DOPPIO_X_2","MATRIMONIALE_X_1","MATRIMONIALE_X_1_SINGOLO_X_1","MATRIMONIALE_X_1_SINGOLO_X_2","MATRIMONIALE_X_2_SINGOLO_X_1","MATRIMONIALE_X_2_SINGOLO_X_2","KING_X_1","KING_X_1_SINGOLO_X_1"]}],"responses":{"200":{"description":"OK"},"401":{"description":"Unauthorized"},"204":{"description":"No Content"},"403":{"description":"Forbidden"}}}},"/api/v1/roomtype/deletebyid/{id}":{"get":{"tags":["room-type-controller"],"summary":"deleteRoomTypeById","operationId":"deleteRoomTypeByIdUsingGET_1","consumes":["application/json"],"produces":["*/*"],"parameters":[{"name":"id","in":"path","description":"id","required":true,"type":"integer","format":"int64"}],"responses":{"200":{"description":"OK"},"401":{"description":"Unauthorized"},"403":{"description":"Forbidden"},"404":{"description":"Not Found"}}}},"/api/v1/roomtype/findall":{"get":{"tags":["room-type-controller"],"summary":"getAllRoomTypes","operationId":"getAllRoomTypesUsingGET","consumes":["application/json"],"produces":["*/*"],"responses":{"200":{"description":"OK","schema":{"type":"array","items":{"$ref":"#/definitions/RoomTypeModel"}}},"401":{"description":"Unauthorized"},"403":{"description":"Forbidden"},"404":{"description":"Not Found"}}}},"/api/v1/roomtype/save":{"post":{"tags":["room-type-controller"],"summary":"insertRoomType","operationId":"insertRoomTypeUsingPOST","consumes":["application/json"],"produces":["*/*"],"parameters":[{"name":"roomTypeId","in":"query","required":false,"type":"integer","format":"int64"},{"name":"typeName","in":"query","required":false,"type":"string"},{"name":"guests","in":"query","required":false,"type":"integer","format":"int32"},{"name":"bedType","in":"query","required":false,"type":"string","enum":["SINGOLO_X_1","SINGOLO_X_2","SINGOLO_X_3","SINGOLO_X_4","DOPPIO_X_1","DOPPIO_X_2","MATRIMONIALE_X_1","MATRIMONIALE_X_1_SINGOLO_X_1","MATRIMONIALE_X_1_SINGOLO_X_2","MATRIMONIALE_X_2_SINGOLO_X_1","MATRIMONIALE_X_2_SINGOLO_X_2","KING_X_1","KING_X_1_SINGOLO_X_1"]}],"responses":{"200":{"description":"OK"},"201":{"description":"Created"},"401":{"description":"Unauthorized"},"403":{"description":"Forbidden"},"404":{"description":"Not Found"}}}},"/api/v1/roomtype/update":{"put":{"tags":["room-type-controller"],"summary":"updateRoomType","operationId":"updateRoomTypeUsingPUT","consumes":["application/json"],"produces":["*/*"],"parameters":[{"name":"roomTypeId","in":"query","required":false,"type":"integer","format":"int64"},{"name":"typeName","in":"query","required":false,"type":"string"},{"name":"guests","in":"query","required":false,"type":"integer","format":"int32"},{"name":"bedType","in":"query","required":false,"type":"string","enum":["SINGOLO_X_1","SINGOLO_X_2","SINGOLO_X_3","SINGOLO_X_4","DOPPIO_X_1","DOPPIO_X_2","MATRIMONIALE_X_1","MATRIMONIALE_X_1_SINGOLO_X_1","MATRIMONIALE_X_1_SINGOLO_X_2","MATRIMONIALE_X_2_SINGOLO_X_1","MATRIMONIALE_X_2_SINGOLO_X_2","KING_X_1","KING_X_1_SINGOLO_X_1"]}],"responses":{"200":{"description":"OK"},"201":{"description":"Created"},"401":{"description":"Unauthorized"},"403":{"description":"Forbidden"},"404":{"description":"Not Found"}}}}},"definitions":{"RoomTypeModel":{"type":"object","properties":{"bedType":{"type":"string","enum":["SINGOLO_X_1","SINGOLO_X_2","SINGOLO_X_3","SINGOLO_X_4","DOPPIO_X_1","DOPPIO_X_2","MATRIMONIALE_X_1","MATRIMONIALE_X_1_SINGOLO_X_1","MATRIMONIALE_X_1_SINGOLO_X_2","MATRIMONIALE_X_2_SINGOLO_X_1","MATRIMONIALE_X_2_SINGOLO_X_2","KING_X_1","KING_X_1_SINGOLO_X_1"]},"guests":{"type":"integer","format":"int32"},"roomTypeId":{"type":"integer","format":"int64"},"typeName":{"type":"string"}}},"BookingModel":{"type":"object","properties":{"bookingDate":{"type":"string"},"bookingId":{"type":"integer","format":"int64"},"code":{"type":"string"},"customerName":{"type":"string"},"deposit":{"type":"string"},"details":{"type":"string"},"guests":{"type":"integer","format":"int32"},"nightNumbers":{"type":"integer","format":"int32"},"paid":{"type":"string","enum":["PAGATO","NON_PAGATO"]},"roomId":{"type":"integer","format":"int32"},"sourceBooking":{"type":"string","enum":["BOOKING","EXTERNAL"]},"total":{"type":"string"}}},"RoomModel":{"type":"object","properties":{"roomId":{"type":"integer","format":"int64"},"roomNumber":{"type":"integer","format":"int32"},"roomTypeModel":{"$ref":"#/definitions/RoomTypeModel"}}}}}
